{"total_occurrences": "66", "occurrences_by_year": {"2019": "3", "2011": "2", "2005": "2", "1990": "1", "2017": "6", "2010": "6", "2004": "1", "1986": "1", "2016": "6", "2009": "2", "2001": "2", "1982": "1", "2015": "6", "2008": "2", "2000": "1", "1977": "1", "2014": "6", "2007": "1", "1999": "2", "1928": "1", "2013": "6", "2006": "2", "1995": "1", "1926": "1", "2012": "3"}, "total_categories": {"REMOTE SENSING ": "22", "HISTORY PHILOSOPHY OF SCIENCE ": "2", "LIMNOLOGY ": "1", "IMAGING SCIENCE PHOTOGRAPHIC TECHNOLOGY ": "15", "PHYSICS APPLIED ": "2", "MARINE FRESHWATER BIOLOGY ": "1", "ENVIRONMENTAL SCIENCES ": "14", "AGRICULTURE MULTIDISCIPLINARY ": "1", "MATERIALS SCIENCE MULTIDISCIPLINARY ": "1", "GEOGRAPHY PHYSICAL ": "7", "ANATOMY MORPHOLOGY ": "1", "MATHEMATICAL COMPUTATIONAL BIOLOGY ": "1", "MATHEMATICS ": "7", "ART ": "1", "METEOROLOGY ATMOSPHERIC SCIENCES ": "1", "ENGINEERING ELECTRICAL ELECTRONIC ": "6", "ASTRONOMY ASTROPHYSICS ": "1", "MICROBIOLOGY ": "1", "FORESTRY ": "6", "BIOTECHNOLOGY APPLIED MICROBIOLOGY ": "1", "NEUROSCIENCES ": "1", "GEOSCIENCES MULTIDISCIPLINARY ": "5", "COMPUTER SCIENCE INFORMATION SYSTEMS ": "1", "OCEANOGRAPHY ": "1", "WATER RESOURCES ": "5", "COMPUTER SCIENCE INTERDISCIPLINARY APPLICATIONS ": "1", "OPTICS ": "1", "ECOLOGY ": "4", "CULTURAL STUDIES ": "1", "PHYSICS CONDENSED MATTER ": "1", "MATHEMATICS APPLIED ": "4", "ENGINEERING MARINE ": "1", "PHYSICS PARTICLES FIELDS ": "1", "PLANT SCIENCES ": "3", "EVOLUTIONARY BIOLOGY ": "1", "POLITICAL SCIENCE ": "1", "BIODIVERSITY CONSERVATION ": "2", "GEOCHEMISTRY GEOPHYSICS ": "1", "SOIL SCIENCE ": "1", "COMPUTER SCIENCE THEORY METHODS ": "2", "GREEN SUSTAINABLE SCIENCE TECHNOLOGY ": "1", "STATISTICS PROBABILITY ": "1", "ENGINEERING ENVIRONMENTAL ": "2", "HUMANITIES MULTIDISCIPLINARY ": "1", "TELECOMMUNICATIONS ": "1", "GEOLOGY ": "2", "INSTRUMENTS INSTRUMENTATION ": "1"}, "sorting_name": "hyperspatial", "categories_by_year": {"2019": {"FORESTRY ": "1", "MATHEMATICS ": "1", "PHYSICS APPLIED ": "1", "MATERIALS SCIENCE MULTIDISCIPLINARY ": "1", "MATHEMATICS APPLIED ": "1", "PHYSICS CONDENSED MATTER ": "1"}, "2011": {"MATHEMATICAL COMPUTATIONAL BIOLOGY ": "1", "REMOTE SENSING ": "1"}, "2005": {"ENVIRONMENTAL SCIENCES ": "1", "REMOTE SENSING ": "1", "SOIL SCIENCE ": "1", "IMAGING SCIENCE PHOTOGRAPHIC TECHNOLOGY ": "1"}, "1990": {"ENGINEERING ELECTRICAL ELECTRONIC ": "1"}, "2017": {"REMOTE SENSING ": "2", "GEOGRAPHY PHYSICAL ": "1", "HUMANITIES MULTIDISCIPLINARY ": "1", "AGRICULTURE MULTIDISCIPLINARY ": "1", "GEOLOGY ": "1", "METEOROLOGY ATMOSPHERIC SCIENCES ": "1", "ENVIRONMENTAL SCIENCES ": "1", "GEOSCIENCES MULTIDISCIPLINARY ": "1"}, "2010": {"ANATOMY MORPHOLOGY ": "1", "IMAGING SCIENCE PHOTOGRAPHIC TECHNOLOGY ": "1", "NEUROSCIENCES ": "1", "ART ": "1", "INSTRUMENTS INSTRUMENTATION ": "1", "PHYSICS APPLIED ": "1", "CULTURAL STUDIES ": "1", "MARINE FRESHWATER BIOLOGY ": "1", "PLANT SCIENCES ": "1", "ENGINEERING ELECTRICAL ELECTRONIC ": "1", "MATHEMATICS ": "1", "REMOTE SENSING ": "1", "ENVIRONMENTAL SCIENCES ": "1"}, "2004": {"ENVIRONMENTAL SCIENCES ": "1", "IMAGING SCIENCE PHOTOGRAPHIC TECHNOLOGY ": "1", "REMOTE SENSING ": "1"}, "1986": {"BIOTECHNOLOGY APPLIED MICROBIOLOGY ": "1", "MICROBIOLOGY ": "1"}, "2016": {"ENVIRONMENTAL SCIENCES ": "2", "ENGINEERING ELECTRICAL ELECTRONIC ": "1", "TELECOMMUNICATIONS ": "1", "HISTORY PHILOSOPHY OF SCIENCE ": "2", "POLITICAL SCIENCE ": "1", "WATER RESOURCES ": "1", "MATHEMATICS ": "2", "REMOTE SENSING ": "1"}, "2009": {"ENVIRONMENTAL SCIENCES ": "2", "IMAGING SCIENCE PHOTOGRAPHIC TECHNOLOGY ": "2", "REMOTE SENSING ": "2"}, "2001": {"COMPUTER SCIENCE INFORMATION SYSTEMS ": "1", "COMPUTER SCIENCE THEORY METHODS ": "1", "FORESTRY ": "1"}, "1982": {"COMPUTER SCIENCE THEORY METHODS ": "1", "MATHEMATICS APPLIED ": "1", "STATISTICS PROBABILITY ": "1"}, "2015": {"GEOGRAPHY PHYSICAL ": "2", "GEOSCIENCES MULTIDISCIPLINARY ": "1", "MATHEMATICS APPLIED ": "1", "REMOTE SENSING ": "2", "IMAGING SCIENCE PHOTOGRAPHIC TECHNOLOGY ": "1", "OPTICS ": "1", "ENVIRONMENTAL SCIENCES ": "1", "MATHEMATICS ": "1", "WATER RESOURCES ": "1", "FORESTRY ": "1"}, "2008": {"ENVIRONMENTAL SCIENCES ": "2", "ECOLOGY ": "1", "REMOTE SENSING ": "1", "BIODIVERSITY CONSERVATION ": "1", "IMAGING SCIENCE PHOTOGRAPHIC TECHNOLOGY ": "1"}, "2000": {"BIODIVERSITY CONSERVATION ": "1", "ECOLOGY ": "1"}, "1977": {"EVOLUTIONARY BIOLOGY ": "1", "PLANT SCIENCES ": "1"}, "2014": {"ENGINEERING ELECTRICAL ELECTRONIC ": "2", "ENGINEERING ENVIRONMENTAL ": "1", "LIMNOLOGY ": "1", "ENVIRONMENTAL SCIENCES ": "2", "GEOGRAPHY PHYSICAL ": "1", "MATHEMATICS APPLIED ": "1", "IMAGING SCIENCE PHOTOGRAPHIC TECHNOLOGY ": "2", "GEOLOGY ": "1", "WATER RESOURCES ": "1", "REMOTE SENSING ": "2"}, "2007": {"REMOTE SENSING ": "1"}, "1999": {"COMPUTER SCIENCE INTERDISCIPLINARY APPLICATIONS ": "1", "FORESTRY ": "1", "WATER RESOURCES ": "1", "ENGINEERING MARINE ": "1", "OCEANOGRAPHY ": "1"}, "1928": {"MATHEMATICS ": "1"}, "2013": {"REMOTE SENSING ": "4", "GEOSCIENCES MULTIDISCIPLINARY ": "2", "FORESTRY ": "1", "IMAGING SCIENCE PHOTOGRAPHIC TECHNOLOGY ": "3", "ECOLOGY ": "1", "GEOCHEMISTRY GEOPHYSICS ": "1", "GEOGRAPHY PHYSICAL ": "2", "ENGINEERING ELECTRICAL ELECTRONIC ": "1"}, "2006": {"IMAGING SCIENCE PHOTOGRAPHIC TECHNOLOGY ": "2", "GEOGRAPHY PHYSICAL ": "1", "GEOSCIENCES MULTIDISCIPLINARY ": "1", "REMOTE SENSING ": "2"}, "1995": {"ASTRONOMY ASTROPHYSICS ": "1", "PHYSICS PARTICLES FIELDS ": "1"}, "1926": {"MATHEMATICS ": "1"}, "2012": {"ECOLOGY ": "1", "FORESTRY ": "1", "PLANT SCIENCES ": "1", "ENGINEERING ENVIRONMENTAL ": "1", "GREEN SUSTAINABLE SCIENCE TECHNOLOGY ": "1", "REMOTE SENSING ": "1", "ENVIRONMENTAL SCIENCES ": "1", "IMAGING SCIENCE PHOTOGRAPHIC TECHNOLOGY ": "1", "WATER RESOURCES ": "1"}}}